borgor/__init__.py
borgor/akatsukiapi.py
borgor/beatmap.py
borgor/osuapi.py
borgor/osuapiv2.py
borgor/replay.py
borgor/simplebeatmap.py
borgor/utils.py
borgor-0.1.9.dist-info/METADATA
borgor-0.1.9.dist-info/WHEEL
borgor-0.1.9.dist-info/top_level.txt
borgor-0.1.9.dist-info/RECORD
